frappeframework/__init__.py
frappeframework-0.0.1.dist-info/LICENSE
frappeframework-0.0.1.dist-info/WHEEL
frappeframework-0.0.1.dist-info/METADATA
frappeframework-0.0.1.dist-info/RECORD
