Metadata-Version: 2.1
Name: frappeframework
Version: 0.0.1
Summary: Frappe Framework
Author-email: frappe <developers@frappe.io>
Classifier: License :: OSI Approved :: MIT License
Project-URL: Home, https://frappeframework.com
